tests
vmupdate
