Metadata-Version: 1.1
Name: vmupdate
Version: 0.3.0
Summary: Command line utility used to keep your virtual machines up to date.
Home-page: https://github.com/corwintanner/vmupdate
Author: Corwin Tanner
Author-email: corwintanner@gmail.com
License: The MIT License (MIT)
